Metadata-Version: 2.1
Name: django-exo-role
Version: 1.8
Summary: Use roles system with Django
Home-page: https://github.com/exolever/django-exo-role
Author: marfyl
Author-email: marfyl.dev@gmail.com
License: MIT
Keywords: python,django,exo,role
Platform: UNKNOWN
Classifier: Development Status :: 5 - Production/Stable
Classifier: Environment :: Web Environment
Classifier: Framework :: Django :: 2.0
Classifier: Intended Audience :: Developers
Classifier: License :: OSI Approved :: BSD License
Classifier: Natural Language :: English
Classifier: Operating System :: OS Independent
Classifier: Programming Language :: Python :: Implementation :: PyPy
Classifier: Programming Language :: Python
Classifier: Programming Language :: Python :: 3.7
License-File: LICENSE
License-File: AUTHORS.rst
Requires-Dist: django (<3.0)
Requires-Dist: django-appconf
Requires-Dist: django-model-utils
Requires-Dist: django-filter
Requires-Dist: djangorestframework
Requires-Dist: psycopg2 (==2.8.6)
Requires-Dist: pyaml
